LICENSE
MANIFEST.in
README.md
setup.cfg
setup.py
Ctl/VERSION
Ctl/requirements-docs.txt
Ctl/requirements-test.txt
Ctl/requirements.txt
src/grainy/__init__.py
src/grainy/const.py
src/grainy/core.py
src/grainy.egg-info/PKG-INFO
src/grainy.egg-info/SOURCES.txt
src/grainy.egg-info/dependency_links.txt
src/grainy.egg-info/requires.txt
src/grainy.egg-info/top_level.txt
src/grainy.egg-info/zip-safe